src/design/57segme.v
`timescale 1ns / 1ps

module sevseg(
    input  [3:0] bcd,       // Entrada BCD de 4 bits (0-9)
    output reg [6:0] segments // Salidas de los segmentos (a-g)
);
    always @(*) begin
        case (bcd)
            4'b0000: segments = 7'b1000000; // 0
            4'b0001: segments = 7'b1111001; // 1
            4'b0010: segments = 7'b0100100; // 2
            4'b0011: segments = 7'b0110000; // 3
            4'b0100: segments = 7'b0011001; // 4
            4'b0101: segments = 7'b0010010; // 5
            4'b0110: segments = 7'b0000010; // 6
            4'b0111: segments = 7'b1111000; // 7
            4'b1000: segments = 7'b0000000; // 8
            4'b1001: segments = 7'b0010000; // 9
            4'b1010: segments = 7'b0001000; // A
            4'b1011: segments = 7'b0000011; // b
            4'b1100: segments = 7'b1000110; // C
            4'b1101: segments = 7'b0100001; // d
            4'b1110: segments = 7'b0000110; // E
            4'b1111: segments = 7'b0001110; // F
            default: segments = 7'b1100011; // Apagado
        endcase
    end
endmodule

src/design/4infoled.v
`timescale 1ns / 1ps

module display_7bits_leds (
    input [6:0] coregido,
    output reg [6:0] led
);
    always @* begin
        led[0] = ~coregido[0];
        led[1] = ~coregido[1];
        led[2] = ~coregido[2];
        led[3] = ~coregido[3];
        led[4] = ~coregido[4];
        led[5] = ~coregido[5];
        led[6] = ~coregido[6];
    end
endmodule

src/design/3correccion.v
`timescale 1ns / 1ps

module correccion_error(
  input  [6:0] dataRaw,
  input  [2:0] sindrome,
  output reg [6:0] correccion,
  output reg [3:0] dataCorrecta
);
  always @(*) begin
    correccion = dataRaw;
    if (sindrome != 3'b000) begin
        case (sindrome)
            3'b001: correccion[0] = ~correccion[0]; // Bit 1
            3'b010: correccion[1] = ~correccion[1]; // Bit 2
            3'b011: correccion[2] = ~correccion[2]; 
            3'b100: correccion[3] = ~correccion[3];
            3'b101: correccion[4] = ~correccion[4];
            3'b110: correccion[5] = ~correccion[5];
            3'b111: correccion[6] = ~correccion[6];
            default: /* no action */;
        endcase
    end
    
    dataCorrecta[3] = correccion[6];
    dataCorrecta[2] = correccion[5];
    dataCorrecta[1] = correccion[4];
    dataCorrecta[0] = correccion[2];
  end
endmodule

src/design/2error.v
`timescale 1ns / 1ps

module hamming_detection (
  input [6:0] dataRaw,
  output reg [2:0] posError
);
  always @(*) begin
    posError[0] = dataRaw[0] ^ dataRaw[2] ^ dataRaw[4] ^ dataRaw[6];
    posError[1] = dataRaw[1] ^ dataRaw[2] ^ dataRaw[5] ^ dataRaw[6];
    posError[2] = dataRaw[3] ^ dataRaw[4] ^ dataRaw[5] ^ dataRaw[6];
  end
endmodule

src/design/1hamming.v
`timescale 1ns / 1ps

module hamming74 (
  input [3:0] in,
  output reg [6:0] ou
);
  reg d3, d5, d6, d7;
  reg p1, p2, p4;

  always @(*) begin
    d7 = in[3];
    d6 = in[2];
    d5 = in[1];
    d3 = in[0];
    p1 = d3 ^ d5 ^ d7;
    p2 = d3 ^ d6 ^ d7;
    p4 = d5 ^ d6 ^ d7;
    
    ou[6] = d7;
    ou[5] = d6;
    ou[4] = d5;
    ou[3] = p4;
    ou[2] = d3;
    ou[1] = p2;
    ou[0] = p1;
  end
endmodule

src/design/modulotop.v
`timescale 1ns / 1ps

module top (
    input  [3:0] in,              // 4 bits de datos originales
    input  [6:0] dataRaw,         // Código Hamming con error manual (7 switches)
    input        selector,        // 0 = usar encoder | 1 = usar switches con error
    output [6:0] led,             // Muestra los 7 bits corregidos
    output [6:0] segments,        // Muestra el dato corregido en hexadecimal (4 bits)
    output [6:0] segments_error   // Muestra el bit donde se detectó el error
);

    // Señales internas
    wire [6:0] dataRaw_from_encoder;
    wire [6:0] dataRaw_muxed;
    wire [2:0] posError;
    wire [6:0] dataCorregido;
    wire [3:0] dataCorrecta;
    wire [3:0] errorDisplay; // Valor a mostrar en el display de error

    // Codificador Hamming 7,4 (convierte 4 bits en 7 bits)
    hamming74 encoder (
        .in(in),
        .ou(dataRaw_from_encoder)
    );

    // Multiplexor: si selector = 0 usa el valor del codificador; si = 1, usa el valor manual (con error)
    assign dataRaw_muxed = selector ? dataRaw : dataRaw_from_encoder;

    // Detección de errores
    hamming_detection detector (
        .dataRaw(dataRaw_muxed),
        .posError(posError)
    );

    // Corrección de errores: corrige el bit erróneo y extrae los 4 bits de dato original
    correccion_error corrector (
        .dataRaw(dataRaw_muxed),
        .sindrome(posError),
        .correccion(dataCorregido),
        .dataCorrecta(dataCorrecta)
    );

    // Visualización en LED (se invierte la señal, ya que los LED son activos en bajo)
    display_7bits_leds display (
        .coregido(dataCorregido),
        .led(led)
    );
    
    // Mostrar el dato corregido (4 bits) en el display de 7 segmentos
    sevseg display_hex(
        .bcd(dataCorrecta),
        .segments(segments)
    );
    
    // Convertir posError (3 bits) a 4 bits para mostrarlo en hexadecimal:
    // Si no hay error (posError == 000), se muestra 0.
    assign errorDisplay = (posError == 3'b000) ? 4'd0 : {1'b0, posError};

    // Mostrar el bit en el que se detectó el error en otro display de 7 segmentos
    sevseg display_error(
        .bcd(errorDisplay),
        .segments(segments_error)
    );

endmodule

src/sim/hammin_tb.v
`timescale 1ns/1ps

module top_tb;

    // === Señales para top ===
    reg [3:0] in;
    reg [6:0] dataRaw;
    reg       selector;
    wire [6:0] led;
    wire [6:0] segments;
    wire [6:0] segments_error;

    top uut (
        .in(in),
        .dataRaw(dataRaw),
        .selector(selector),
        .led(led),
        .segments(segments),
        .segments_error(segments_error)
    );

    // === Señales y pruebas para módulos individuales ===

    // hamming74
    reg  [3:0] in_enc;
    wire [6:0] out_enc;
    hamming74 encoder_tb (
        .in(in_enc),
        .ou(out_enc)
    );

    // hamming_detection
    reg  [6:0] data_det;
    wire [2:0] pos_error;
    hamming_detection detection_tb (
        .dataRaw(data_det),
        .posError(pos_error)
    );

    // correccion_error
    reg  [6:0] data_corr;
    reg  [2:0] sindrome;
    wire [6:0] corregido;
    wire [3:0] data_correcta;
    correccion_error correction_tb (
        .dataRaw(data_corr),
        .sindrome(sindrome),
        .correccion(corregido),
        .dataCorrecta(data_correcta)
    );

    // display_7bits_leds
    reg  [6:0] coregido_leds;
    wire [6:0] leds_out;
    display_7bits_leds leds_tb (
        .coregido(coregido_leds),
        .led(leds_out)
    );

    // sevseg
    reg  [3:0] bcd_val;
    wire [6:0] seg_out;
    sevseg seg_tb (
        .bcd(bcd_val),
        .segments(seg_out)
    );

    initial begin
        $dumpfile("top_tb.vcd");
        $dumpvars(0, top_tb);
        $display("Iniciando pruebas...");
        $display("==================================== Pruebas individuales ======================================");

        // === hamming74 ===
        in_enc = 4'b1010;
        #1;
        $display("hamming74: in=%b => out=%b", in_enc, out_enc);
        in_enc = 4'b1111;
        #1;
        $display("hamming74: in=%b => out=%b", in_enc, out_enc);
        in_enc = 4'b0000;
        #1;
        $display("hamming74: in=%b => out=%b", in_enc, out_enc);

        $display("================================================================================================");
        $display("================================================================================================");


        // === hamming_detection ===
        data_det = 7'b1000101;  
        #1;
        $display("hamming_detection: dataRaw=%b => posError=%b", data_det, pos_error);
        data_det = 7'b0000001;  
        #1;
        $display("hamming_detection: dataRaw=%b => posError=%b", data_det, pos_error);
        data_det = 7'b0111111;  
        #1;
        $display("hamming_detection: dataRaw=%b => posError=%b", data_det, pos_error);

        $display("================================================================================================");
        $display("================================================================================================");

        // === correccion_error ===
        data_corr = 7'b1000101;
        sindrome = 3'b101;  
        #1;
        $display("correccion_error: in=%b, sindrome=%b => corregido=%b, dato=%b",
                 data_corr, sindrome, corregido, data_correcta);
        data_corr = 7'b0000001;
        sindrome = 3'b001;  
        #1;
        $display("correccion_error: in=%b, sindrome=%b => corregido=%b, dato=%b",
                 data_corr, sindrome, corregido, data_correcta);
        data_corr = 7'b0111111;
        sindrome = 3'b111; 
        #1;
        $display("correccion_error: in=%b, sindrome=%b => corregido=%b, dato=%b",
                 data_corr, sindrome, corregido, data_correcta);

        $display("================================================================================================");
        $display("================================================================================================");

        // === display_7bits_leds ===
        coregido_leds = 7'b1010101;
        #1;
        $display("display_7bits_leds: in=%b => leds=%b", coregido_leds, leds_out);
        coregido_leds = 7'b1111111;
        #1;
        $display("display_7bits_leds: in=%b => leds=%b", coregido_leds, leds_out);
        coregido_leds = 7'b0000000;
        #1;
        $display("display_7bits_leds: in=%b => leds=%b", coregido_leds, leds_out);

        $display("================================================================================================");
        $display("================================================================================================");

        // === sevseg ===
        bcd_val = 4'hA; 
        #1;
        $display("sevseg: bcd=%h => seg=%b", bcd_val, seg_out);
        bcd_val = 4'h0; 
        #1;
        $display("sevseg: bcd=%h => seg=%b", bcd_val, seg_out);
        bcd_val = 4'h2; 
        #1;
        $display("sevseg: bcd=%h => seg=%b", bcd_val, seg_out);
        bcd_val = 4'h9; 
        #1;
        $display("sevseg: bcd=%h => seg=%b", bcd_val, seg_out);
        

         $display("================================================================================================");
        $display("================================================================================================");
        $display("========================== Pruebas del modulo top ================================");

        // === Pruebas top ===
        $display("Caso | selector | in (ref) | dataRaw (error) | Corrected (7-bit) | 7seg (hex)");
        
        // Caso 1: Modo encoder (selector = 0)
        selector = 0;
        in = 4'b1010;
        dataRaw = 7'b0000000; 
        #10;
        $display("  1   |   %b    |   %b   |    %b    |      %b      |  %b", 
                  selector, in, dataRaw, led, segments);
        
        // Caso 2: Modo error (selector = 1)
        selector = 1;
        in = 4'b1010;
        dataRaw = 7'b1000101;
        #10;
        $display("  2   |   %b    |   %b   |    %b    |      %b      |  %b", 
                  selector, in, dataRaw, led, segments);

        // Caso 3: Otro valor en modo error
        selector = 1;
        in = 4'b0110;
        dataRaw = 7'b0110010;
        #10;
        $display("  3   |   %b    |   %b   |    %b    |      %b      |  %b", 
                  selector, in, dataRaw, led, segments);

        $finish;
    end

endmodule

src/build/top_tb.vcd
$date
	Fri Apr 04 20:17:36 2025
$end
$version
	Icarus Verilog
$end
$timescale
	1ps
$end
$scope module top_tb $end
$var wire 7 ! segments_error [6:0] $end
$var wire 7 " segments [6:0] $end
$var wire 7 # seg_out [6:0] $end
$var wire 3 $ pos_error [2:0] $end
$var wire 7 % out_enc [6:0] $end
$var wire 7 & leds_out [6:0] $end
$var wire 7 ' led [6:0] $end
$var wire 4 ( data_correcta [3:0] $end
$var wire 7 ) corregido [6:0] $end
$var reg 4 * bcd_val [3:0] $end
$var reg 7 + coregido_leds [6:0] $end
$var reg 7 , dataRaw [6:0] $end
$var reg 7 - data_corr [6:0] $end
$var reg 7 . data_det [6:0] $end
$var reg 4 / in [3:0] $end
$var reg 4 0 in_enc [3:0] $end
$var reg 1 1 selector $end
$var reg 3 2 sindrome [2:0] $end
$scope module correction_tb $end
$var wire 7 3 dataRaw [6:0] $end
$var wire 3 4 sindrome [2:0] $end
$var reg 7 5 correccion [6:0] $end
$var reg 4 6 dataCorrecta [3:0] $end
$upscope $end
$scope module detection_tb $end
$var wire 7 7 dataRaw [6:0] $end
$var reg 3 8 posError [2:0] $end
$upscope $end
$scope module encoder_tb $end
$var wire 4 9 in [3:0] $end
$var reg 1 : d3 $end
$var reg 1 ; d5 $end
$var reg 1 < d6 $end
$var reg 1 = d7 $end
$var reg 7 > ou [6:0] $end
$var reg 1 ? p1 $end
$var reg 1 @ p2 $end
$var reg 1 A p4 $end
$upscope $end
$scope module leds_tb $end
$var wire 7 B coregido [6:0] $end
$var reg 7 C led [6:0] $end
$upscope $end
$scope module seg_tb $end
$var wire 4 D bcd [3:0] $end
$var reg 7 E segments [6:0] $end
$upscope $end
$scope module uut $end
$var wire 7 F dataRaw [6:0] $end
$var wire 4 G in [3:0] $end
$var wire 1 1 selector $end
$var wire 7 H segments_error [6:0] $end
$var wire 7 I segments [6:0] $end
$var wire 3 J posError [2:0] $end
$var wire 7 K led [6:0] $end
$var wire 4 L errorDisplay [3:0] $end
$var wire 7 M dataRaw_muxed [6:0] $end
$var wire 7 N dataRaw_from_encoder [6:0] $end
$var wire 7 O dataCorregido [6:0] $end
$var wire 4 P dataCorrecta [3:0] $end
$scope module corrector $end
$var wire 7 Q dataRaw [6:0] $end
$var wire 3 R sindrome [2:0] $end
$var reg 7 S correccion [6:0] $end
$var reg 4 T dataCorrecta [3:0] $end
$upscope $end
$scope module detector $end
$var wire 7 U dataRaw [6:0] $end
$var reg 3 V posError [2:0] $end
$upscope $end
$scope module display $end
$var wire 7 W coregido [6:0] $end
$var reg 7 X led [6:0] $end
$upscope $end
$scope module display_error $end
$var wire 4 Y bcd [3:0] $end
$var reg 7 Z segments [6:0] $end
$upscope $end
$scope module display_hex $end
$var wire 4 [ bcd [3:0] $end
$var reg 7 \ segments [6:0] $end
$upscope $end
$scope module encoder $end
$var wire 4 ] in [3:0] $end
$var reg 1 ^ d3 $end
$var reg 1 _ d5 $end
$var reg 1 ` d6 $end
$var reg 1 a d7 $end
$var reg 7 b ou [6:0] $end
$var reg 1 c p1 $end
$var reg 1 d p2 $end
$var reg 1 e p4 $end
$upscope $end
$upscope $end
$upscope $end
$enddefinitions $end
$comment Show the parameter values. $end
$dumpall
$end
#0
$dumpvars
xe
xd
xc
bx b
xa
x`
x_
x^
bx ]
bx \
bx [
b1100011 Z
b0xxx Y
bx X
bx W
bx V
bx U
bx T
bx S
bx R
bx Q
bx P
bx O
bx N
bx M
b0xxx L
bx K
bx J
bx I
b1100011 H
bx G
bx F
bx E
bx D
bx C
bx B
0A
1@
0?
b1010010 >
1=
0<
1;
0:
b1010 9
bx 8
bx 7
bx 6
bx 5
bx 4
bx 3
bx 2
x1
b1010 0
bx /
bx .
bx -
bx ,
bx +
bx *
bx )
bx (
bx '
bx &
b1010010 %
bx $
bx #
bx "
b1100011 !
$end
#1000
b1111111 %
b1111111 >
1A
1?
1:
1<
b1111 0
b1111 9
#2000
b0 %
b0 >
0A
0@
0?
0:
0;
0<
0=
b0 0
b0 9
#3000
b101 $
b101 8
b1000101 .
b1000101 7
#4000
b1 $
b1 8
b1 .
b1 7
#5000
b111 $
b111 8
b111111 .
b111111 7
#6000
b1011 (
b1011 6
b1010101 )
b1010101 5
b101 2
b101 4
b1000101 -
b1000101 3
#7000
b0 (
b0 6
b0 )
b0 5
b1 2
b1 4
b1 -
b1 3
#8000
b1111 (
b1111 6
b1111111 )
b1111111 5
b111 2
b111 4
b111111 -
b111111 3
#9000
b101010 &
b101010 C
b1010101 +
b1010101 B
#10000
b0 &
b0 C
b1111111 +
b1111111 B
#11000
b1111111 &
b1111111 C
b0 +
b0 B
#12000
b1000 #
b1000 E
b1010 *
b1010 D
#13000
b1000000 #
b1000000 E
b0 *
b0 D
#14000
b100100 #
b100100 E
b10 *
b10 D
#15000
b10000 #
b10000 E
b1001 *
b1001 D
#16000
b1000000 !
b1000000 H
b1000000 Z
b1000 "
b1000 I
b1000 \
b101101 '
b101101 K
b101101 X
b0 L
b0 Y
b1010 P
b1010 T
b1010 [
b1010010 O
b1010010 S
b1010010 W
b0 J
b0 R
b0 V
b1010010 M
b1010010 Q
b1010010 U
b1010010 N
b1010010 b
0e
1d
0c
0^
1_
0`
1a
b0 ,
b0 F
b1010 /
b1010 G
b1010 ]
01
#26000
b10010 !
b10010 H
b10010 Z
b11 "
b11 I
b11 \
b101010 '
b101010 K
b101010 X
b101 L
b101 Y
b1011 P
b1011 T
b1011 [
b1010101 O
b1010101 S
b1010101 W
b101 J
b101 R
b101 V
b1000101 M
b1000101 Q
b1000101 U
b1000101 ,
b1000101 F
11
#36000
b1111001 !
b1111001 H
b1111001 Z
b10 "
b10 I
b10 \
b1001100 '
b1001100 K
b1001100 X
b1 L
b1 Y
b110 P
b110 T
b110 [
b110011 O
b110011 S
b110011 W
b1 J
b1 R
b1 V
b110010 M
b110010 Q
b110010 U
b110011 N
b110011 b
1c
1`
0a
b110010 ,
b110010 F
b110 /
b110 G
b110 ]
